stoneforge/__init__.py
stoneforge/data_replacement/__init__.py
stoneforge/data_replacement/evaluation.py
stoneforge/data_replacement/fit.py
stoneforge/data_replacement/mldr_project.py
stoneforge/data_replacement/predict.py
stoneforge/data_replacement/settings.py
stoneforge/datasets/__init__.py
stoneforge/datasets/data_info.txt
stoneforge/datasets/dataload.py
stoneforge/datasets/las2.py
stoneforge/inversion/__init__.py
stoneforge/inversion/regularized_acoustic_reflectivy_inversion.py
stoneforge/inversion/viability_study/__init__.py
stoneforge/inversion/viability_study/bayes.py
stoneforge/machine_learning/__init__.py
stoneforge/machine_learning/evaluation.py
stoneforge/machine_learning/fit.py
stoneforge/machine_learning/predict.py
stoneforge/machine_learning/settings.py
stoneforge/machine_learning/validation.py
stoneforge/mlp_classification/__init__.py
stoneforge/mlp_classification/evaluation.py
stoneforge/mlp_classification/fit.py
stoneforge/mlp_classification/predict.py
stoneforge/mlp_classification/settings.py
stoneforge/mlp_classification/validation.py
stoneforge/mlp_regression/__init__.py
stoneforge/mlp_regression/evaluation.py
stoneforge/mlp_regression/fit.py
stoneforge/mlp_regression/predict.py
stoneforge/mlp_regression/settings.py
stoneforge/mlp_regression/validation.py
stoneforge/petrophysics/__init__.py
stoneforge/petrophysics/helpers.py
stoneforge/petrophysics/porosity.py
stoneforge/petrophysics/shale_volume.py
stoneforge/petrophysics/total_organic_carbon_content.py
stoneforge/petrophysics/water_saturation.py
stoneforge/preprocessing/__init__.py
stoneforge/preprocessing/data_management.py
stoneforge/preprocessing/data_processing.py
stoneforge/preprocessing/las2.py
stoneforge/preprocessing/las_pandas.py
stoneforge/pseudo_wells/__init__.py
stoneforge/pseudo_wells/lithology_generator.py
stoneforge/pseudo_wells/monte_carlo_simulations.py
stoneforge/pseudo_wells/pseudo_tools.py
stoneforge/rock_physics/__init__.py
stoneforge/rock_physics/elastic_constants.py
stoneforge-0.1.6.dist-info/LICENSE
stoneforge-0.1.6.dist-info/METADATA
stoneforge-0.1.6.dist-info/WHEEL
stoneforge-0.1.6.dist-info/top_level.txt
stoneforge-0.1.6.dist-info/RECORD
