Metadata-Version: 2.1
Name: stoneforge
Version: 0.1.6
Summary: Geophysics equations, algorithms and methods
Home-page: https://github.com/giecaruff/stoneforge
Author: GIECAR - UFF
License: MIT
Requires-Python: ==3.12.6
License-File: LICENSE
Requires-Dist: numpy==1.26.4
Requires-Dist: pytest==8.1.1
Requires-Dist: scipy==1.13.0
Requires-Dist: scikit-learn==1.4.2
Requires-Dist: xgboost==2.0.3
Requires-Dist: matplotlib==3.8.4
Requires-Dist: pandas==2.2.2
Requires-Dist: catboost==1.2.5
Requires-Dist: lightgbm==4.3.0
